cvtlib/__init__.py
cvtlib/drawing.py
cvtlib/files.py
cvtlib/image.py
cvtlib/video.py
cvtlib-0.8.6.dist-info/LICENSE
cvtlib-0.8.6.dist-info/METADATA
cvtlib-0.8.6.dist-info/WHEEL
cvtlib-0.8.6.dist-info/top_level.txt
cvtlib-0.8.6.dist-info/RECORD
